matterlab_pumps/__init__.py
matterlab_pumps/base_pump.py
matterlab_pumps/continuous_dual_syringe.py
matterlab_pumps/jkem_pump.py
matterlab_pumps/longer_peri.py
matterlab_pumps/longer_pump.py
matterlab_pumps/runze_pump.py
matterlab_pumps/tecan_centris_pump.py
matterlab_pumps/tecan_xc_pump.py
matterlab_pumps/tecan_xlp_pump.py
matterlab_pumps-1.0.4.dist-info/licenses/LICENSE
matterlab_pumps-1.0.4.dist-info/METADATA
matterlab_pumps-1.0.4.dist-info/WHEEL
matterlab_pumps-1.0.4.dist-info/entry_points.txt
matterlab_pumps-1.0.4.dist-info/top_level.txt
matterlab_pumps-1.0.4.dist-info/RECORD
