Metadata-Version: 2.4
Name: matterlab_pumps
Version: 1.0.4
Summary: A Python API for the pumps in the Matter Lab.
Author: Han Hao, Martin Seifrid, Tony C. Wu
License-Expression: MIT
Project-URL: homepage, https://gitlab.com/aspuru-guzik-group/self-driving-lab/devices/pumps
Keywords: pump,automation,matterlab
Classifier: Intended Audience :: Science/Research
Classifier: Programming Language :: Python :: 3
Classifier: Programming Language :: Python :: 3 :: Only
Classifier: Topic :: Scientific/Engineering
Classifier: Topic :: Scientific/Engineering :: Chemistry
Classifier: Topic :: System :: Hardware
Classifier: Topic :: System :: Hardware :: Hardware Drivers
Classifier: Topic :: System :: Hardware :: Universal Serial Bus (USB)
Requires-Python: >=3.7
License-File: LICENSE
Requires-Dist: matterlab_serial_device
Provides-Extra: dev
Requires-Dist: mypy>=0; extra == "dev"
Requires-Dist: pre-commit; extra == "dev"
Requires-Dist: pytest>=7; extra == "dev"
Requires-Dist: pytest-cov>=3; extra == "dev"
Requires-Dist: pytest-mock>=3; extra == "dev"
Requires-Dist: pytest-rerunfailures; extra == "dev"
Requires-Dist: pytest-timeout; extra == "dev"
Requires-Dist: ruff; extra == "dev"
Dynamic: license-file
